{
  "type": "image",
  "images": [],
  "isActivity": false,
  "urn": "urn:li:activity:6775327611246714880",
  "url": "https://www.linkedin.com/posts/honzajavorek_online-klub-na-httpsjuniorguruclub-umo%C5%BE%C5%88uje-activity-6775327611246714880-_k1-",
  "timeSincePosted": "5yr",
  "shareUrn": "urn:li:share:6775327610760163328",
  "text": "Online klub na https://junior.guru/club umožňuje probrat kariérní rozhodnutí, dostat zpětnou vazbu na pohovor, nechat si poradit při těžkém rozhodování. A to jak ve skupině, tak i jen se mnou v soukromé zprávě. Přidej se a zkus to - prvních 14 dní je zdarma, nemusíš ani zadávat kartu.",
  "attributes": [],
  "comments": [],
  "reactions": [
    {
      "type": "LIKE",
      "profile": {
        "firstName": "Kateřina",
        "lastName": "P.",
        "occupation": "Currently on maternity leave",
        "id": "498811395",
        "publicId": "katerinapaulinova",
        "profileId": "ACoAAB27QgMB-LtkvlGwxNcB-N_aZb3iLmTAnn0"
      }
    },
    {
      "type": "LIKE",
      "profile": {
        "firstName": "Kateřina",
        "lastName": "Večeřová",
        "occupation": "Always learning",
        "id": "350226850",
        "publicId": "kateřina-večeřová-6aa35999",
        "profileId": "ACoAABTgCaIBcqqf6ZEPOYr_qFlK1MOSgWO3EO4"
      }
    },
    {
      "type": "LIKE",
      "profile": {
        "firstName": "Jana",
        "lastName": "Nováková Stará",
        "occupation": "Founder at Czech Wellness Institute",
        "id": "161000370",
        "publicId": "janastara",
        "profileId": "ACoAAAmYq7IBuzhl4URXOeq6B12fEl9bTL42ouM"
      }
    },
    {
      "type": "LIKE",
      "profile": {
        "firstName": "Renata",
        "lastName": "Ouředníková",
        "occupation": "Head of Production of Women for Women",
        "id": "619140749",
        "publicId": "renata-ouředníková-065423153",
        "profileId": "ACoAACTnVo0Bn8sI0ng22XleF5SnlKdMztgiAmg"
      }
    },
    {
      "type": "LIKE",
      "profile": {
        "firstName": "Dora",
        "lastName": "Carvan",
        "occupation": "Learning & Development, Events, CSR and InCom in NTT DATA",
        "id": "212971262",
        "publicId": "dora-carvan-3123a75b",
        "profileId": "ACoAAAyxrv4BES1IEjBXMularacGfbAC0gp4rDI"
      }
    },
    {
      "type": "EMPATHY",
      "profile": {
        "firstName": "Lenka",
        "lastName": "Erbenova",
        "occupation": "Application Developer at Barclays",
        "id": "361531956",
        "publicId": "lenkaerbenova",
        "profileId": "ACoAABWMijQBlQzoTAse2JjfcJmbjz4dAQnIsQs"
      }
    },
    {
      "type": "LIKE",
      "profile": {
        "firstName": "Jiri",
        "lastName": "Gunka",
        "occupation": "cyp",
        "id": "106076066",
        "publicId": "jiri-gunka",
        "profileId": "ACoAAAZSl6IBReZE2DpEw1yYFc7o_nXXv7ld64Y"
      }
    },
    {
      "type": "LIKE",
      "profile": {
        "firstName": "Bara",
        "lastName": "M.",
        "occupation": "IT Business Analyst, Green:Code - Working on MySkoda App",
        "id": "403529541",
        "publicId": "bara-mikusova",
        "profileId": "ACoAABgNX0UBfOm-Qcjh24GeHIJqCCo1Q0vHOc0"
      }
    },
    {
      "type": "LIKE",
      "profile": {
        "firstName": "Petr",
        "lastName": "Žížek",
        "occupation": "Průvodce cykly bohatství 📈",
        "id": "229451762",
        "publicId": "petr-žížek-702a1464",
        "profileId": "ACoAAA2tJ_IB7sP5S6LHxlMS2UfNxfoAbaFpW4w"
      }
    },
    {
      "type": "LIKE",
      "profile": {
        "firstName": "Magda",
        "lastName": "Karlíková",
        "occupation": "Člověk roste náročnými úkoly",
        "id": "873324137",
        "publicId": "magda-karlíková-ab5583204",
        "profileId": "ACoAADQN3mkB9WsckQR7-n8RLSKeg_43IErbmv4"
      }
    }
  ],
  "numShares": 1,
  "numLikes": 25,
  "numComments": 0,
  "canReact": true,
  "canPostComments": true,
  "canShare": true,
  "commentingDisabled": false,
  "allowedCommentersScope": "ALL",
  "rootShare": true,
  "shareAudience": "PUBLIC",
  "author": {
    "firstName": "Honza",
    "lastName": "Javorek",
    "occupation": "Tvořím junior.guru, které pomáhá juniorním programátorům",
    "id": "8517488",
    "publicId": "honzajavorek",
    "profileId": "ACoAAACB93ABHHj4UI2winetGMZHboHlZIZojJA"
  },
  "authorProfileId": "honzajavorek",
  "authorType": "Person",
  "authorName": "Honza Javorek",
  "authorProfileUrl": "https://www.linkedin.com/in/honzajavorek?miniProfileUrn=urn%3Ali%3Afs_miniProfile%3AACoAAACB93ABHHj4UI2winetGMZHboHlZIZojJA",
  "authorUrn": "urn:li:member:8517488",
  "postedAtTimestamp": 1615363982021,
  "postedAtISO": "2021-03-10T08:13:02.021Z",
  "inputUrl": "https://www.linkedin.com/in/honzajavorek/"
}
