{
  "type": "image",
  "images": [],
  "isActivity": false,
  "urn": "urn:li:activity:6934793596688592898",
  "url": "https://www.linkedin.com/posts/honzajavorek_tatanka-pastvedlepasti-podcast-activity-6934793596688592898-y5Xv",
  "timeSincePosted": "4yr",
  "shareUrn": "urn:li:share:6934793595908444161",
  "text": "PÁTÝ DÍL PODCASTU JE TOP! 🎙 Petr Přibil z jižní Moravy alias #Tatanka, původně lesník a obchoďák vypráví o své cestě do IT. A že je to parádní vypravěč! Na závěr přihodil i historku o legendární opravě traktoru Lakatoš 🚜\n\nCo Tatankovi na začátku nejvíce pomohlo a co by udělal jinak? Jak se k programování dostal? Co by poradil těm, kdo chtějí odejít z rozjeté kariéry na juniorní místo v IT? Co se stalo, když ve své první práci nenašel potřebné zázemí? #pastvedlepasti\n\nNový díl si můžete pustit na kterékoliv běžné podcastové platformě, nebo i přímo na junior.guru/podcast\n\nLíbí se vám náš #podcast? Chcete, aby měla Pavlina F. radost a točila další díly? Dejte nám v aplikacích pěkné hodnocení. Do 5. června nás taky můžete nominovat do ankety podcastroku.cz ⭐️",
  "attributes": [
    {
      "start": 28,
      "length": 11,
      "type": "PROFILE_MENTION",
      "profile": {
        "firstName": "Petr",
        "lastName": "Přibil",
        "occupation": "Global Sales Manager | Specialty Lubricants",
        "id": "132002824",
        "publicId": "petr-pribil",
        "profileId": "ACoAAAfeNAgBoN0dEx44SvOJMrr1wXdzXDehEck"
      }
    },
    {
      "start": 620,
      "length": 10,
      "type": "PROFILE_MENTION",
      "profile": {
        "firstName": "Pavlina",
        "lastName": "F.",
        "occupation": "Host @ Junior Guru podcast.",
        "id": "190849253",
        "publicId": "pavlinafronkova",
        "profileId": "ACoAAAtgIOUBXx7J1YrKIrXM8ShTElmmhautDR4"
      }
    }
  ],
  "comments": [
    {
      "time": 1653387026125,
      "link": "https://www.linkedin.com/feed/update/urn:li:activity:6934793596688592898?commentUrn=urn%3Ali%3Acomment%3A%28activity%3A6934793596688592898%2C6934807817220440066%29&dashCommentUrn=urn%3Ali%3Afsd_comment%3A%286934807817220440066%2Curn%3Ali%3Aactivity%3A6934793596688592898%29",
      "text": "Diky moc Pavlina F. za pozvani a perfektni atmosferu pri nataceni, plus Honza Javorek za veskere to spiskani🙂🤞",
      "entities": [
        {
          "start": 9,
          "length": 10,
          "type": "PROFILE_MENTION",
          "profile": {
            "firstName": "Pavlina",
            "lastName": "F.",
            "occupation": "Host @ Junior Guru podcast.",
            "id": "190849253",
            "publicId": "pavlinafronkova",
            "profileId": "ACoAAAtgIOUBXx7J1YrKIrXM8ShTElmmhautDR4"
          }
        },
        {
          "start": 72,
          "length": 13,
          "type": "PROFILE_MENTION",
          "profile": {
            "firstName": "Honza",
            "lastName": "Javorek",
            "occupation": "Tvořím junior.guru, které pomáhá juniorním programátorům",
            "id": "8517488",
            "publicId": "honzajavorek",
            "profileId": "ACoAAACB93ABHHj4UI2winetGMZHboHlZIZojJA"
          }
        }
      ],
      "pinned": false,
      "originalLanguage": "Slovak",
      "author": {
        "firstName": "Petr",
        "lastName": "Přibil",
        "occupation": "Global Sales Manager | Specialty Lubricants",
        "id": "132002824",
        "publicId": "petr-pribil",
        "profileId": "ACoAAAfeNAgBoN0dEx44SvOJMrr1wXdzXDehEck",
        "distance": "OUT_OF_NETWORK"
      }
    }
  ],
  "reactions": [
    {
      "type": "LIKE",
      "profile": {
        "firstName": "Petr",
        "lastName": "Messner",
        "occupation": "Full-stack software engineer and developer",
        "id": "21519263",
        "publicId": "messa",
        "profileId": "ACoAAAFIW58BHQuf7UmFIL0JxAANFW73V79_YOY"
      }
    },
    {
      "type": "PRAISE",
      "profile": {
        "firstName": "Marketa",
        "lastName": "Lieblova",
        "occupation": "Senior Consultant at Husted | EMA Partners International Czech and Slovak",
        "id": "14502552",
        "publicId": "mlie100",
        "profileId": "ACoAAADdSpgB2XEd1YsrCL6hDG1f8efGXlBaEGM"
      }
    },
    {
      "type": "LIKE",
      "profile": {
        "firstName": "Martin",
        "lastName": "Bolek",
        "occupation": "People and Community Leader | Startups Advisor for HR, Community and Marketing | Seasoned HR, TA, and Community professional | TOP 20 Biggest CZ Linkedin profiles",
        "id": "242323201",
        "publicId": "martinbolek",
        "profileId": "ACoAAA5xjwEB-5I0z2Ur7gyCn2MoA1wU5jE2R8I"
      }
    },
    {
      "type": "LIKE",
      "profile": {
        "firstName": "Eva",
        "lastName": "Kopecká",
        "occupation": "🚀TAS • Formuji příběhy a propojuji svět. Jsem specialistka na External Communication a Public Relations🌐✨",
        "id": "945744642",
        "publicId": "eva-kopecká-b16889224",
        "profileId": "ACoAADhe6wIBYb8DALgIyVg1hbdo9xFkslfDic0"
      }
    },
    {
      "type": "LIKE",
      "profile": {
        "firstName": "Katerina",
        "lastName": "Maresova Ali",
        "occupation": "Employer Branding v IT | Moderátorka smitio komunity 🎤 | Pomáhám firmám budovat značku a oslovit talenty skrze autentický obsah.",
        "id": "21030863",
        "publicId": "katerina-maresova-smitio",
        "profileId": "ACoAAAFA588Br07-uohoO-ZxDwmW5hiuFHo-v7s"
      }
    },
    {
      "type": "LIKE",
      "profile": {
        "firstName": "Long",
        "lastName": "Do",
        "occupation": "Seize the day!",
        "id": "767755711",
        "publicId": "long-do-0a7153195",
        "profileId": "ACoAAC3DBb8Bapv7X_MAj8YCk4a-D5t4wIvwEXA"
      }
    },
    {
      "type": "LIKE",
      "profile": {
        "firstName": "Marie",
        "lastName": "Fardová",
        "occupation": "QA / IT Operations / Application Support (L2/L3) | Incident & Problem coordination",
        "id": "984876474",
        "publicId": "marie-fardova",
        "profileId": "ACoAADq0BboBQ_KRV4mEctJhGCkj367mI-MHLFY"
      }
    },
    {
      "type": "LIKE",
      "profile": {
        "firstName": "Martin",
        "lastName": "Holomek",
        "occupation": "Breaking things safely so production doesn’t have to.",
        "id": "950609242",
        "publicId": "martin-holomek-10a435226",
        "profileId": "ACoAADipJVoBUKy1-ggmu1NEjjtKbSmjY5ujyrk"
      }
    },
    {
      "type": "LIKE",
      "profile": {
        "firstName": "Daniel",
        "lastName": "Rozehnal",
        "occupation": "Software engineering student at FI MUNI.",
        "id": "731425708",
        "publicId": "daniel-rozehnal-924b52184",
        "profileId": "ACoAACuYq6wBw_NUyA50V0fvku83SMXkgexoGa8"
      }
    },
    {
      "type": "LIKE",
      "profile": {
        "firstName": "Lukáš",
        "lastName": "Tuček",
        "occupation": "🔎 QA Automation Engineer | Web & Mobile Testing (Playwright, Maestro) | 🚘 Majitel ve společnosti LT Detailing",
        "id": "567367047",
        "publicId": "lukastucek7",
        "profileId": "ACoAACHRVYcBZjOpRsnCmT-1OV2S9E1GcTqhk1s"
      }
    }
  ],
  "numShares": 0,
  "numLikes": 30,
  "numComments": 1,
  "canReact": true,
  "canPostComments": true,
  "canShare": true,
  "commentingDisabled": false,
  "allowedCommentersScope": "ALL",
  "rootShare": true,
  "shareAudience": "PUBLIC",
  "author": {
    "firstName": "Honza",
    "lastName": "Javorek",
    "occupation": "Tvořím junior.guru, které pomáhá juniorním programátorům",
    "id": "8517488",
    "publicId": "honzajavorek",
    "profileId": "ACoAAACB93ABHHj4UI2winetGMZHboHlZIZojJA"
  },
  "authorProfileId": "honzajavorek",
  "authorType": "Person",
  "authorName": "Honza Javorek",
  "authorProfileUrl": "https://www.linkedin.com/in/honzajavorek?miniProfileUrn=urn%3Ali%3Afs_miniProfile%3AACoAAACB93ABHHj4UI2winetGMZHboHlZIZojJA",
  "authorUrn": "urn:li:member:8517488",
  "postedAtTimestamp": 1653383635685,
  "postedAtISO": "2022-05-24T09:13:55.685Z",
  "inputUrl": "https://www.linkedin.com/in/honzajavorek/"
}
