{
  "type": "image",
  "images": [],
  "isActivity": false,
  "urn": "urn:li:activity:6919249480575782912",
  "url": "https://www.linkedin.com/posts/honzajavorek_careerswitch-finance-podcast-activity-6919249480575782912-hA7h",
  "timeSincePosted": "4yr",
  "shareUrn": "urn:li:share:6919249479774670849",
  "text": "HOSTEM V PODCASTU 🐷 Dokonce i v podcastu o financích na vás vyskočí Javorek s těmi svými juniory. Přede mnou se neschováte! Už přemýšlím, kde si domluvit angažmá v relaci pro zahrádkáře.\n\nVe 40. epizodě Rozbité prasátko najdete rozhovor se mnou a Pavel Polcr. Pavel, původně finančník z Olomouce, se i díky junior.guru dostal do IT a o své cestě píše na blog itnoob.cz\n\nJe reálné zvýšit svůj pravidelný příjem tím, že změníte kariéru a bude z vás programátorka nebo programátor? Je to tak jednoduché, jak se říká? Jak to vůbec udělat? Jaké finanční ohodnocení vlastně očekávat? A je IT jenom o penězích?\n\nV rozhovoru, který se mnou a s Pavlem vedl „prasátko“ Jakub Dvořák, se to všechno dovíte 🎧 #careerswitch #finance #podcast",
  "attributes": [
    {
      "start": 203,
      "length": 16,
      "type": "COMPANY_NAME",
      "company": {
        "name": "Rozbité prasátko",
        "universalName": "rozbiteprasatko",
        "active": true,
        "showcase": false,
        "entityUrn": "urn:li:fs_miniCompany:20562484"
      }
    },
    {
      "start": 247,
      "length": 11,
      "type": "PROFILE_MENTION",
      "profile": {
        "firstName": "Pavel",
        "lastName": "Polcr",
        "occupation": "Software Engineer | Storyteller | LinkedIn Enthusiast and Mentor | I help other techies build a personal brand on LinkedIn | Fuelling growth of software engineers through Software Engineering Tales Podcast",
        "id": "266067406",
        "publicId": "pavel-polcr",
        "profileId": "ACoAAA_b3c4BTAcvcf2VyIBHi_X2WWOWGNyt1ZI"
      }
    },
    {
      "start": 659,
      "length": 12,
      "type": "PROFILE_MENTION",
      "profile": {
        "firstName": "Jakub",
        "lastName": "Dvořák",
        "occupation": "Dvořák & Zedník Wealth Management | Rozbité prasátko | Book Author | Podcast Host | ex-Data scientist",
        "id": "446728226",
        "publicId": "dvoorajak",
        "profileId": "ACoAABqgiCIBGae91KbE1yHZSbzOLo87v5ifelI"
      }
    }
  ],
  "comments": [
    {
      "time": 1649678280325,
      "link": "https://www.linkedin.com/feed/update/urn:li:activity:6919249480575782912?commentUrn=urn%3Ali%3Acomment%3A%28activity%3A6919249480575782912%2C6919252209876508673%29&dashCommentUrn=urn%3Ali%3Afsd_comment%3A%286919252209876508673%2Curn%3Ali%3Aactivity%3A6919249480575782912%29",
      "text": "Přihodím odkaz na díl https://rozbiteprasatko.cz/epizoda40/",
      "entities": [],
      "pinned": false,
      "originalLanguage": "Czech",
      "author": {
        "firstName": "Honza",
        "lastName": "Javorek",
        "occupation": "Tvořím junior.guru, které pomáhá juniorním programátorům",
        "id": "8517488",
        "publicId": "honzajavorek",
        "profileId": "ACoAAACB93ABHHj4UI2winetGMZHboHlZIZojJA",
        "distance": "OUT_OF_NETWORK"
      }
    },
    {
      "time": 1649678041030,
      "link": "https://www.linkedin.com/feed/update/urn:li:activity:6919249480575782912?commentUrn=urn%3Ali%3Acomment%3A%28activity%3A6919249480575782912%2C6919251206200545280%29&dashCommentUrn=urn%3Ali%3Afsd_comment%3A%286919251206200545280%2Curn%3Ali%3Aactivity%3A6919249480575782912%29",
      "text": "Díky za propojení a příležitost doplnit skvělý rozhovor s tebou, Honza Javorek. Rozhodně zajímavá zkušenost!",
      "entities": [
        {
          "start": 65,
          "length": 13,
          "type": "PROFILE_MENTION",
          "profile": {
            "firstName": "Honza",
            "lastName": "Javorek",
            "occupation": "Tvořím junior.guru, které pomáhá juniorním programátorům",
            "id": "8517488",
            "publicId": "honzajavorek",
            "profileId": "ACoAAACB93ABHHj4UI2winetGMZHboHlZIZojJA"
          }
        }
      ],
      "pinned": false,
      "originalLanguage": "Czech",
      "author": {
        "firstName": "Pavel",
        "lastName": "Polcr",
        "occupation": "Software Engineer | Storyteller | LinkedIn Enthusiast and Mentor | I help other techies build a personal brand on LinkedIn | Fuelling growth of software engineers through Software Engineering Tales Podcast",
        "id": "266067406",
        "publicId": "pavel-polcr",
        "profileId": "ACoAAA_b3c4BTAcvcf2VyIBHi_X2WWOWGNyt1ZI",
        "distance": "OUT_OF_NETWORK"
      }
    }
  ],
  "reactions": [
    {
      "type": "LIKE",
      "profile": {
        "firstName": "Veronika ",
        "lastName": "Vacatová",
        "occupation": "Analytik IT auditu ve společnosti KPMG Czech Republic",
        "id": "823217745",
        "publicId": "veronika-kopicova",
        "profileId": "ACoAADERTlEBR16jtxiyB4-QHxs8Dr_dt-KxLNA"
      }
    },
    {
      "type": "LIKE",
      "profile": {
        "firstName": "Diana",
        "lastName": "Nemčeková",
        "occupation": "Frontend Developer at SAP Signavio",
        "id": "340727197",
        "publicId": "diana-nemcekova",
        "profileId": "ACoAABRPFZ0B0af2F8_icLbBOQpvX7jszeotbI4"
      }
    },
    {
      "type": "PRAISE",
      "profile": {
        "firstName": "Pavel",
        "lastName": "Filip",
        "occupation": "Začátečním bodem všech úspěchů je zaměření na cíl.",
        "id": "942714715",
        "publicId": "pavel-filip-5b7868223",
        "profileId": "ACoAADgwr1sBjcqNqmu1jWyiy2WMLTxFqYTlUc4"
      }
    },
    {
      "type": "LIKE",
      "profile": {
        "firstName": "Eliška",
        "lastName": "Gatnerová",
        "occupation": "Business Recruiter",
        "id": "792721886",
        "publicId": "eliška-gatnerová1",
        "profileId": "ACoAAC8_-d4BET2bmilz7nVrgBS96h49jwv8Wps"
      }
    },
    {
      "type": "LIKE",
      "profile": {
        "firstName": "Vendy",
        "lastName": "Frýzlová",
        "occupation": "Software engineer at SentinelOne",
        "id": "635157598",
        "publicId": "vendula-fryzlova",
        "profileId": "ACoAACXbvF4BMYBoSNyPUWfavc6vba7zzNusFQw"
      }
    },
    {
      "type": "LIKE",
      "profile": {
        "firstName": "Jakub",
        "lastName": "Dvořák",
        "occupation": "Dvořák & Zedník Wealth Management | Rozbité prasátko | Book Author | Podcast Host | ex-Data scientist",
        "id": "446728226",
        "publicId": "dvoorajak",
        "profileId": "ACoAABqgiCIBGae91KbE1yHZSbzOLo87v5ifelI"
      }
    },
    {
      "type": "LIKE",
      "profile": {
        "firstName": "Klára",
        "lastName": "B.",
        "occupation": "IT HR Specialist - Recruiter | Founder @najdikarieru",
        "id": "652675821",
        "publicId": "klárabojnák",
        "profileId": "ACoAACbnCu0BvNff6ceF7vZWMt_0Y6_QFKi4kSc"
      }
    },
    {
      "type": "LIKE",
      "profile": {
        "firstName": "Pavel",
        "lastName": "Polcr",
        "occupation": "Software Engineer | Storyteller | LinkedIn Enthusiast and Mentor | I help other techies build a personal brand on LinkedIn | Fuelling growth of software engineers through Software Engineering Tales Podcast",
        "id": "266067406",
        "publicId": "pavel-polcr",
        "profileId": "ACoAAA_b3c4BTAcvcf2VyIBHi_X2WWOWGNyt1ZI"
      }
    }
  ],
  "numShares": 1,
  "numLikes": 8,
  "numComments": 3,
  "canReact": true,
  "canPostComments": true,
  "canShare": true,
  "commentingDisabled": false,
  "allowedCommentersScope": "ALL",
  "rootShare": true,
  "shareAudience": "PUBLIC",
  "author": {
    "firstName": "Honza",
    "lastName": "Javorek",
    "occupation": "Tvořím junior.guru, které pomáhá juniorním programátorům",
    "id": "8517488",
    "publicId": "honzajavorek",
    "profileId": "ACoAAACB93ABHHj4UI2winetGMZHboHlZIZojJA"
  },
  "authorProfileId": "honzajavorek",
  "authorType": "Person",
  "authorName": "Honza Javorek",
  "authorProfileUrl": "https://www.linkedin.com/in/honzajavorek?miniProfileUrn=urn%3Ali%3Afs_miniProfile%3AACoAAACB93ABHHj4UI2winetGMZHboHlZIZojJA",
  "authorUrn": "urn:li:member:8517488",
  "postedAtTimestamp": 1649677629608,
  "postedAtISO": "2022-04-11T11:47:09.608Z",
  "inputUrl": "https://www.linkedin.com/in/honzajavorek/"
}
