{
  "type": "image",
  "images": [],
  "isActivity": true,
  "activityDescription": "Honza Javorek reposted this",
  "activityOfUser": {
    "firstName": "Honza",
    "lastName": "Javorek",
    "occupation": "Tvořím junior.guru, které pomáhá juniorním programátorům",
    "id": "8517488",
    "publicId": "honzajavorek",
    "profileId": "ACoAAACB93ABHHj4UI2winetGMZHboHlZIZojJA"
  },
  "urn": "urn:li:activity:7388495617129488384",
  "url": "https://www.linkedin.com/posts/pycon-namibia_pyconna26-pyconnamibia2026-activity-7388494913056788480-8JXe",
  "timeSincePosted": "6mo",
  "shareUrn": "urn:li:share:7388494912012484608",
  "text": "🎉 Call for Proposals is Now Open! 🎉\n\nWe’re excited to announce that PyCon Namibia 2026 is now accepting talk, tutorial, and workshop proposals!\n🗓️ Deadline: Dec 1, 2025\n🔗 Learn More & Submit Here: https://lnkd.in/deCar9-n\n\nWhether you’re an experienced speaker or stepping onto the stage for the first time, this is your chance to share your knowledge, ideas, and passion with the Python community. \nWe welcome topics across all areas of Python, from AI and data science to web development, education, and community stories and etc.\n#PyConNA26 #PyConNamibia2026 PyCon Africa DjangoCon Africa Django Software Foundation",
  "attributes": [
    {
      "start": 562,
      "length": 12,
      "type": "COMPANY_NAME",
      "company": {
        "name": "PyCon Africa",
        "universalName": "pyconafrica",
        "active": true,
        "showcase": false,
        "entityUrn": "urn:li:fs_miniCompany:28473205"
      }
    },
    {
      "start": 575,
      "length": 16,
      "type": "COMPANY_NAME",
      "company": {
        "name": "DjangoCon Africa",
        "universalName": "djcafrica",
        "active": true,
        "showcase": false,
        "entityUrn": "urn:li:fs_miniCompany:27097305"
      }
    },
    {
      "start": 592,
      "length": 26,
      "type": "COMPANY_NAME",
      "company": {
        "name": "Django Software Foundation",
        "universalName": "django-software-foundation",
        "active": true,
        "showcase": false,
        "entityUrn": "urn:li:fs_miniCompany:8356765"
      }
    }
  ],
  "comments": [],
  "reactions": [
    {
      "type": "LIKE",
      "profile": {
        "firstName": "Selma",
        "lastName": "Iileka",
        "occupation": "Namibian University of Science and Technology",
        "id": "1499716958",
        "publicId": "selma-iileka-91230335a",
        "profileId": "ACoAAFlj3V4BnNoR9pMA0WF031cNGdUmS7LmYm0"
      }
    },
    {
      "type": "LIKE",
      "profile": {
        "firstName": "Seth",
        "lastName": "Mensah",
        "occupation": "Rewriting Africa’s tech, Open Source and Security narrative, one initiative at a time",
        "id": "862159617",
        "publicId": "cerebrocerberus",
        "profileId": "ACoAADNjgwEB_lC_DSf09NEYZvVtJz88JRhutdQ"
      }
    },
    {
      "type": "EMPATHY",
      "profile": {
        "firstName": "Prince",
        "lastName": "Asiedu",
        "occupation": "Software Engineer | Open Source | Software Supply Chain Security",
        "id": "629120643",
        "publicId": "princeoforhasiedu",
        "profileId": "ACoAACV_noMBx1ZNnvegVNgRXiXY40qb0JCBdkI"
      }
    },
    {
      "type": "LIKE",
      "profile": {
        "firstName": "Abdoul Ben Fatao",
        "lastName": "SANON",
        "occupation": "Computer Science Student | Tech & Entrepreneurship Builder | President, BIT English Club | Team Leader Sales Exchange AIESEC | Founder, SABF Team | Co-founder, Coders_Pro | Web & Digital Innovation",
        "id": "1502359946",
        "publicId": "sabf-sanon",
        "profileId": "ACoAAFmMMYoBfQ02BFnkE1LW1uAkkoEN7931zrc"
      }
    },
    {
      "type": "PRAISE",
      "profile": {
        "firstName": "Camilla",
        "lastName": "Montonen",
        "occupation": "ml/search/solutions puffin’",
        "id": "785723627",
        "publicId": "camilla-montonen-20b17919b",
        "profileId": "ACoAAC7VMOsBgyBbe9YwKhKSPDIz6SZPZ4haIic"
      }
    },
    {
      "type": "LIKE",
      "profile": {
        "firstName": "José Pablo",
        "lastName": "Barrantes",
        "occupation": "Science & Analytics | MLOps | Fraud Prevention",
        "id": "277242751",
        "publicId": "jose-barrantes",
        "profileId": "ACoAABCGY38BCDeIWcYteZWFHM4D1viRoYH2u_8"
      }
    },
    {
      "type": "LIKE",
      "profile": {
        "firstName": "Pinias",
        "lastName": "Shilongo",
        "occupation": "Student",
        "id": "1366646834",
        "publicId": "pinias-shilongo-70282b321",
        "profileId": "ACoAAFF1YDIBLd1Ep2N2Niu6fSQpFX3xHl-YE40"
      }
    },
    {
      "type": "LIKE",
      "profile": {
        "firstName": "Kelelo",
        "lastName": "Ngwato",
        "occupation": "Data & AI Specialist | MSc Applied AI & BSc Business Analytics | Unlocking data-driven flow with Python, machine learning & dashboards",
        "id": "837544270",
        "publicId": "kelelo-ngwato",
        "profileId": "ACoAADHr6U4BKas2nz0dBMOI9Tey8vTLIXoJCG0"
      }
    },
    {
      "type": "LIKE",
      "profile": {
        "firstName": "Giuliano",
        "lastName": "Bianco",
        "occupation": "| Researcher Coordinator | Journalist | Dev | Data",
        "id": "119175769",
        "publicId": "giuliano-marcus-bianco",
        "profileId": "ACoAAAcaelkB467D9HfEnJkeVkhmqCMSOUOhdiM"
      }
    },
    {
      "type": "LIKE",
      "profile": {
        "firstName": "kahilu",
        "lastName": "makai",
        "occupation": "Software Developer | Experienced IT Professional",
        "id": "783769741",
        "publicId": "kahilu-makai-55159619a",
        "profileId": "ACoAAC63YI0BcQOV-mK8O5j8TkWIc9gLWcKK9kQ"
      }
    }
  ],
  "numShares": 18,
  "numLikes": 58,
  "numComments": 0,
  "canReact": true,
  "canPostComments": true,
  "canShare": true,
  "commentingDisabled": false,
  "allowedCommentersScope": "ALL",
  "rootShare": true,
  "shareAudience": "PUBLIC",
  "author": {
    "name": "PyCon Namibia",
    "universalName": "pycon-namibia",
    "active": true,
    "showcase": false,
    "entityUrn": "urn:li:fs_miniCompany:91586071"
  },
  "authorType": "Company",
  "authorProfileId": "company",
  "authorFollowersCount": "1,059",
  "authorName": "PyCon Namibia",
  "authorProfileUrl": "https://www.linkedin.com/company/pycon-namibia/posts",
  "authorUrn": "urn:li:company:91586071",
  "postedAtTimestamp": 1761554626734,
  "postedAtISO": "2025-10-27T08:43:46.734Z",
  "inputUrl": "https://www.linkedin.com/in/honzajavorek/"
}
