{
  "type": "article",
  "article": {
    "type": "FIRST_PARTY",
    "urn": "urn:li:linkedInArticle:7425172595916001281",
    "url": "https://www.linkedin.com/pulse/leden-2026-ve-sv%25C4%259Bt%25C4%259B-junior%25C5%25AF-honza-javorek-4zxaf?trackingId=%2BCwsuEyqQCiL4zLOGHibFg%3D%3D",
    "title": "Leden 2026 ve světě IT juniorů",
    "description": "Ahoj, tady robotické kuře z junior.guru! Mám pro tebe aktuální dávku novinek. Baví tě tyhle novinky a chceš si je číst pravidelně? Nespoléhej se na al"
  },
  "isActivity": false,
  "urn": "urn:li:activity:7425173154828034050",
  "url": "https://www.linkedin.com/posts/honzajavorek_za%C4%8D%C3%ADn%C3%A1%C5%A1-v-it-v-tomhle-newsletteru-najde%C5%A1-activity-7425173154828034050-Yd3Z",
  "timeSincePosted": "3mo",
  "shareUrn": "urn:li:ugcPost:7425173154412695552",
  "text": "Začínáš v IT? V tomhle newsletteru najdeš pozvánky, kurzy, podcasty, přednášky, články a další zdroje, které tě posunou a namotivují.",
  "attributes": [],
  "comments": [],
  "reactions": [
    {
      "type": "LIKE",
      "profile": {
        "firstName": "Lenka",
        "lastName": "Matějová",
        "occupation": "...",
        "id": "212362653",
        "publicId": "lenka-matějová-0791535b",
        "profileId": "ACoAAAyoZZ0BOS1B_PZN1qbkv-R_Pd20LKcx4w4"
      }
    },
    {
      "type": "LIKE",
      "profile": {
        "firstName": "Táňa",
        "lastName": "Váchová",
        "occupation": "📌 administrativa ⊃ podpora ⊃ empatie",
        "id": "1399848350",
        "publicId": "tanavachova",
        "profileId": "ACoAAFNv_Z4BxskkxA5XZSQetiT0HKCBk4rbPGE"
      }
    },
    {
      "type": "EMPATHY",
      "profile": {
        "firstName": "Karla",
        "lastName": "Root",
        "occupation": "Stay calm. Ask AI first, then decide whether to panic. 👣 Data never lie. People do.",
        "id": "420075610",
        "publicId": "karlaroot",
        "profileId": "ACoAABkJ2FoBTyti7b2tWEdLiODfYKDO6El_iog"
      }
    },
    {
      "type": "LIKE",
      "profile": {
        "firstName": "Tomáš",
        "lastName": "Cibulec",
        "occupation": "Python vývojář s přesahem. 🐍",
        "id": "399499541",
        "publicId": "ypsilonxpython",
        "profileId": "ACoAABfP4RUBhhqww_PQuiFQs580Isbr6ZqrqOg"
      }
    },
    {
      "type": "APPRECIATION",
      "profile": {
        "firstName": "Irena",
        "lastName": "Zatloukalova",
        "occupation": "empowering #autisticTalent in Tech 🚀 | Guiding your communication for change | Systemic coaching",
        "id": "99891449",
        "publicId": "izatlouk",
        "profileId": "ACoAAAX0OPkBzZjVvVi08LqhaKA5UMdVz4M5inM"
      }
    },
    {
      "type": "LIKE",
      "profile": {
        "firstName": "Petra",
        "lastName": "Kubita Nulíčková",
        "occupation": "HR Manager v Pale Fire Capital | Head of HR v Aukro | HR consultant and mentor | #sharingiscaring",
        "id": "473833031",
        "publicId": "petranulickova",
        "profileId": "ACoAABw-HkcBifENxX8nxAs2YjwxbI6b2XtAF98"
      }
    },
    {
      "type": "LIKE",
      "profile": {
        "firstName": "Zuzana",
        "lastName": "Bodri",
        "occupation": "QA Engineer | Test Automation Enthusiast | SAP & HRIS Specialist | Czechitas DA Testing Graduate",
        "id": "221016832",
        "publicId": "zuzanabodri",
        "profileId": "ACoAAA0scwABJpACMUjr-uyYFHcpxEGnpoxwrks"
      }
    },
    {
      "type": "LIKE",
      "profile": {
        "firstName": "Veronika",
        "lastName": "Čamborová",
        "occupation": "Frontend developer",
        "id": "1082522617",
        "publicId": "veronika-čamborová",
        "profileId": "ACoAAECF-_kB69byXoaMHs_qzffiv1hqdN_aZ0U"
      }
    },
    {
      "type": "LIKE",
      "profile": {
        "firstName": "Lucie",
        "lastName": "Bízová",
        "occupation": "Dobrý kolektiv - polovina spokojenosti v práci.",
        "id": "831634717",
        "publicId": "lucie-bizova",
        "profileId": "ACoAADGRvR0Bmz6dpuIeGNLxjuTuqXV0VyKLKQw"
      }
    },
    {
      "type": "LIKE",
      "profile": {
        "firstName": "Šimon",
        "lastName": "Kořený",
        "occupation": "Product Owner & Dad | Building great products, raising great humans",
        "id": "283596586",
        "publicId": "fusatytata",
        "profileId": "ACoAABDnVyoBAtj2jNSQ0mKJB84EeAmS3DoPJ5k"
      }
    }
  ],
  "numShares": 0,
  "numLikes": 11,
  "numComments": 0,
  "canReact": true,
  "canPostComments": true,
  "canShare": true,
  "commentingDisabled": false,
  "allowedCommentersScope": "ALL",
  "rootShare": true,
  "shareAudience": "PUBLIC",
  "author": {
    "firstName": "Honza",
    "lastName": "Javorek",
    "occupation": "Tvořím junior.guru, které pomáhá juniorním programátorům",
    "id": "8517488",
    "publicId": "honzajavorek",
    "profileId": "ACoAAACB93ABHHj4UI2winetGMZHboHlZIZojJA"
  },
  "authorProfileId": "honzajavorek",
  "authorType": "Person",
  "authorName": "Honza Javorek",
  "authorProfileUrl": "https://www.linkedin.com/in/honzajavorek?miniProfileUrn=urn%3Ali%3Afs_miniProfile%3AACoAAACB93ABHHj4UI2winetGMZHboHlZIZojJA",
  "authorUrn": "urn:li:member:8517488",
  "postedAtTimestamp": 1770299233157,
  "postedAtISO": "2026-02-05T13:47:13.157Z",
  "inputUrl": "https://www.linkedin.com/in/honzajavorek/"
}
